{"version": "1.2", "metadata": {"title": "illest alive", "beats_in_measure": "4", "BPM": "96", "key": "Bb", "YouTubeID": "ddwo_kcT-WQ", "mode": "2", "duration": "24.89"}, "tracks": {"melody": [{"pitch": 2.0, "isRest": false, "event_on": 0.0, "event_off": 8.0, "event_duration": 8.0}, {"pitch": 2.0, "isRest": false, "event_on": 8.0, "event_off": 16.0, "event_duration": 8.0}, {"pitch": 0.0, "isRest": false, "event_on": 16.0, "event_off": 17.5, "event_duration": 1.5}, {"pitch": 2.0, "isRest": false, "event_on": 17.5, "event_off": 24.0, "event_duration": 6.5}, null, null, {"pitch": -5.0, "isRest": false, "event_on": 25.0, "event_off": 26.0, "event_duration": 1.0}, {"pitch": -3.0, "isRest": false, "event_on": 26.0, "event_off": 26.5, "event_duration": 0.5}, {"pitch": -3.0, "isRest": false, "event_on": 26.5, "event_off": 26.75, "event_duration": 0.25}, {"pitch": 0.0, "isRest": false, "event_on": 26.75, "event_off": 27.75, "event_duration": 1.0}, {"pitch": 0.0, "isRest": false, "event_on": 27.75, "event_off": 28.0, "event_duration": 0.25}, null, null, {"pitch": -5.0, "isRest": false, "event_on": 29.0, "event_off": 30.0, "event_duration": 1.0}, {"pitch": -3.0, "isRest": false, "event_on": 30.0, "event_off": 30.75, "event_duration": 0.75}, {"pitch": 0.0, "isRest": false, "event_on": 30.75, "event_off": 31.25, "event_duration": 0.5}, {"pitch": 0.0, "isRest": false, "event_on": 31.25, "event_off": 31.5, "event_duration": 0.25}, {"pitch": 0.0, "isRest": false, "event_on": 31.5, "event_off": 31.75, "event_duration": 0.25}, {"pitch": 0.0, "isRest": false, "event_on": 31.75, "event_off": 32.0, "event_duration": 0.25}], "chord": [{"root": 2, "bass": 5, "comp_vec": [14, null, 5, null, 9, null, null, null, null], "composition": [14, 5, 9], "quality": "m", "chord_type": 5, "chord_mode": -2, "isRest": false, "event_on": 0.0, "event_off": 3.0, "event_duration": 3.0, "inv": 1, "sus": null, "alter": null, "emb": [], "alter_map": null, "symbol": "dm | F"}, {"root": 0, "bass": 3, "comp_vec": [12, null, 3, null, 7, null, 14, null, null], "composition": [12, 3, 7, 14], "quality": "m", "chord_type": 5, "chord_mode": -2, "isRest": false, "event_on": 3.0, "event_off": 8.0, "event_duration": 5.0, "inv": 1, "sus": null, "alter": null, "emb": ["add9"], "alter_map": null, "symbol": "cm | Eb (add9)"}, {"root": 2, "bass": 5, "comp_vec": [14, null, 5, null, 9, null, null, null, null], "composition": [14, 5, 9], "quality": "m", "chord_type": 5, "chord_mode": -2, "isRest": false, "event_on": 8.0, "event_off": 10.5, "event_duration": 2.5, "inv": 1, "sus": null, "alter": null, "emb": [], "alter_map": null, "symbol": "dm | F"}, {"root": 7, "bass": 7, "comp_vec": [7, 9, null, null, 14, null, null, null, null], "composition": [7, 9, 14], "quality": "m", "chord_type": 5, "chord_mode": -2, "isRest": false, "event_on": 10.5, "event_off": 11.0, "event_duration": 0.5, "inv": 0, "sus": "sus2", "alter": null, "emb": [], "alter_map": null, "symbol": "gm sus2"}, {"root": 0, "bass": 3, "comp_vec": [12, null, 3, null, 7, null, 14, null, null], "composition": [12, 3, 7, 14], "quality": "m", "chord_type": 5, "chord_mode": -2, "isRest": false, "event_on": 11.0, "event_off": 16.0, "event_duration": 5.0, "inv": 1, "sus": null, "alter": null, "emb": ["add9"], "alter_map": null, "symbol": "cm | Eb (add9)"}, {"root": 5, "bass": 5, "comp_vec": [5, null, 9, null, 12, null, null, null, null], "composition": [5, 9, 12], "quality": "", "chord_type": 5, "chord_mode": -2, "isRest": false, "event_on": 16.0, "event_off": 17.5, "event_duration": 1.5, "inv": 0, "sus": null, "alter": null, "emb": [], "alter_map": null, "symbol": "F"}, {"root": 2, "bass": 5, "comp_vec": [14, null, 5, null, 9, null, null, null, null], "composition": [14, 5, 9], "quality": "m", "chord_type": 5, "chord_mode": -2, "isRest": false, "event_on": 17.5, "event_off": 19.0, "event_duration": 1.5, "inv": 1, "sus": null, "alter": null, "emb": [], "alter_map": null, "symbol": "dm | F"}, {"root": 0, "bass": 3, "comp_vec": [12, null, 3, null, 7, null, 14, null, null], "composition": [12, 3, 7, 14], "quality": "m", "chord_type": 5, "chord_mode": -2, "isRest": false, "event_on": 19.0, "event_off": 24.0, "event_duration": 5.0, "inv": 1, "sus": null, "alter": null, "emb": ["add9"], "alter_map": null, "symbol": "cm | Eb (add9)"}, {"root": 9, "bass": 12, "comp_vec": [21, null, 12, null, 15, 19, null, null, null], "composition": [21, 12, 15, 19], "quality": "\u00f8", "chord_type": 7, "chord_mode": -2, "isRest": false, "event_on": 24.0, "event_off": 28.0, "event_duration": 4.0, "inv": 1, "sus": null, "alter": null, "emb": [], "alter_map": null, "symbol": "a\u00f87 | C"}, {"root": 0, "bass": 3, "comp_vec": [12, null, 3, null, 7, 10, null, null, null], "composition": [12, 3, 7, 10], "quality": "m", "chord_type": 7, "chord_mode": -2, "isRest": false, "event_on": 28.0, "event_off": 32.0, "event_duration": 4.0, "inv": 1, "sus": null, "alter": null, "emb": [], "alter_map": null, "symbol": "cm7 | Eb"}]}, "num_measures": 8.0}