{"version": null, "metadata": {"title": "magical 2", "beats_in_measure": "4", "BPM": "157", "key": "C#", "YouTubeID": "omQusTYhl2Y", "mode": "6", "duration": "39.7"}, "tracks": {"melody": [{"pitch": 13.0, "isRest": false, "event_on": 0.0, "event_off": 13.5, "event_duration": 13.5}, null, {"pitch": 13.0, "isRest": false, "event_on": 14.0, "event_off": 14.25, "event_duration": 0.25}, {"pitch": 8.0, "isRest": false, "event_on": 14.25, "event_off": 14.5, "event_duration": 0.25}, {"pitch": 13.0, "isRest": false, "event_on": 14.5, "event_off": 14.75, "event_duration": 0.25}, {"pitch": 15.0, "isRest": false, "event_on": 14.75, "event_off": 15.0, "event_duration": 0.25}, {"pitch": 16.0, "isRest": false, "event_on": 15.0, "event_off": 15.25, "event_duration": 0.25}, {"pitch": 15.0, "isRest": false, "event_on": 15.25, "event_off": 15.5, "event_duration": 0.25}, {"pitch": 16.0, "isRest": false, "event_on": 15.5, "event_off": 15.75, "event_duration": 0.25}, {"pitch": 18.0, "isRest": false, "event_on": 15.75, "event_off": 16.0, "event_duration": 0.25}, {"pitch": 20.0, "isRest": false, "event_on": 16.0, "event_off": 20.0, "event_duration": 4.0}, {"pitch": 18.0, "isRest": false, "event_on": 20.0, "event_off": 22.0, "event_duration": 2.0}, {"pitch": 23.0, "isRest": false, "event_on": 22.0, "event_off": 24.0, "event_duration": 2.0}, {"pitch": 20.0, "isRest": false, "event_on": 24.0, "event_off": 29.0, "event_duration": 5.0}, null, {"pitch": 4.0, "isRest": false, "event_on": 30.0, "event_off": 31.0, "event_duration": 1.0}, {"pitch": 6.0, "isRest": false, "event_on": 31.0, "event_off": 32.0, "event_duration": 1.0}, {"pitch": 8.0, "isRest": false, "event_on": 32.0, "event_off": 35.0, "event_duration": 3.0}, {"pitch": 13.0, "isRest": false, "event_on": 35.0, "event_off": 36.0, "event_duration": 1.0}, {"pitch": 15.0, "isRest": false, "event_on": 36.0, "event_off": 37.5, "event_duration": 1.5}, null, {"pitch": 15.0, "isRest": false, "event_on": 38.0, "event_off": 38.75, "event_duration": 0.75}, {"pitch": 13.0, "isRest": false, "event_on": 38.75, "event_off": 39.5, "event_duration": 0.75}, {"pitch": 15.0, "isRest": false, "event_on": 39.5, "event_off": 40.0, "event_duration": 0.5}, {"pitch": 16.0, "isRest": false, "event_on": 40.0, "event_off": 41.25, "event_duration": 1.25}, null, {"pitch": 18.0, "isRest": false, "event_on": 41.5, "event_off": 43.0, "event_duration": 1.5}, {"pitch": 16.0, "isRest": false, "event_on": 43.0, "event_off": 44.0, "event_duration": 1.0}, {"pitch": 15.0, "isRest": false, "event_on": 44.0, "event_off": 46.0, "event_duration": 2.0}, {"pitch": 15.0, "isRest": false, "event_on": 46.0, "event_off": 46.75, "event_duration": 0.75}, {"pitch": 11.0, "isRest": false, "event_on": 46.75, "event_off": 47.5, "event_duration": 0.75}, {"pitch": 6.0, "isRest": false, "event_on": 47.5, "event_off": 48.0, "event_duration": 0.5}, {"pitch": 8.0, "isRest": false, "event_on": 48.0, "event_off": 56.0, "event_duration": 8.0}, {"pitch": 13.0, "isRest": false, "event_on": 56.0, "event_off": 64.0, "event_duration": 8.0}, null, {"pitch": 8.0, "isRest": false, "event_on": 48.0, "event_off": 49.5, "event_duration": 1.5}, null, {"pitch": 15.0, "isRest": false, "event_on": 50.0, "event_off": 51.25, "event_duration": 1.25}, null, {"pitch": 16.0, "isRest": false, "event_on": 52.0, "event_off": 53.25, "event_duration": 1.25}, null, {"pitch": 18.0, "isRest": false, "event_on": 54.0, "event_off": 54.75, "event_duration": 0.75}, {"pitch": 16.0, "isRest": false, "event_on": 54.75, "event_off": 55.5, "event_duration": 0.75}, {"pitch": 18.0, "isRest": false, "event_on": 55.5, "event_off": 56.0, "event_duration": 0.5}, {"pitch": 20.0, "isRest": false, "event_on": 56.0, "event_off": 60.0, "event_duration": 4.0}, {"pitch": 20.0, "isRest": false, "event_on": 60.0, "event_off": 60.75, "event_duration": 0.75}, {"pitch": 22.0, "isRest": false, "event_on": 60.75, "event_off": 61.5, "event_duration": 0.75}, {"pitch": 23.0, "isRest": false, "event_on": 61.5, "event_off": 62.0, "event_duration": 0.5}, {"pitch": 22.0, "isRest": false, "event_on": 62.0, "event_off": 62.75, "event_duration": 0.75}, {"pitch": 20.0, "isRest": false, "event_on": 62.75, "event_off": 63.5, "event_duration": 0.75}, {"pitch": 18.0, "isRest": false, "event_on": 63.5, "event_off": 64.0, "event_duration": 0.5}, {"pitch": 20.0, "isRest": false, "event_on": 64.0, "event_off": 65.5, "event_duration": 1.5}, {"pitch": 13.0, "isRest": false, "event_on": 65.5, "event_off": 66.0, "event_duration": 0.5}, {"pitch": 20.0, "isRest": false, "event_on": 66.0, "event_off": 67.5, "event_duration": 1.5}, null, {"pitch": 18.0, "isRest": false, "event_on": 68.0, "event_off": 69.5, "event_duration": 1.5}, null, {"pitch": 18.0, "isRest": false, "event_on": 70.0, "event_off": 70.75, "event_duration": 0.75}, {"pitch": 16.0, "isRest": false, "event_on": 70.75, "event_off": 71.5, "event_duration": 0.75}, {"pitch": 15.0, "isRest": false, "event_on": 71.5, "event_off": 71.75, "event_duration": 0.25}, null, {"pitch": 16.0, "isRest": false, "event_on": 72.0, "event_off": 73.25, "event_duration": 1.25}, null, {"pitch": 8.0, "isRest": false, "event_on": 73.5, "event_off": 74.75, "event_duration": 1.25}, null, {"pitch": 16.0, "isRest": false, "event_on": 75.0, "event_off": 76.0, "event_duration": 1.0}, {"pitch": 15.0, "isRest": false, "event_on": 76.0, "event_off": 78.0, "event_duration": 2.0}, {"pitch": 15.0, "isRest": false, "event_on": 78.0, "event_off": 78.75, "event_duration": 0.75}, {"pitch": 11.0, "isRest": false, "event_on": 78.75, "event_off": 79.5, "event_duration": 0.75}, {"pitch": 6.0, "isRest": false, "event_on": 79.5, "event_off": 80.0, "event_duration": 0.5}, {"pitch": 8.0, "isRest": false, "event_on": 80.0, "event_off": 88.0, "event_duration": 8.0}, null, {"pitch": 13.0, "isRest": false, "event_on": 89.0, "event_off": 90.0, "event_duration": 1.0}, null, {"pitch": 16.0, "isRest": false, "event_on": 91.0, "event_off": 92.0, "event_duration": 1.0}, null, {"pitch": 12.0, "isRest": false, "event_on": 93.0, "event_off": 94.0, "event_duration": 1.0}, null, {"pitch": 15.0, "isRest": false, "event_on": 95.0, "event_off": 96.0, "event_duration": 1.0}], "chord": [{"root": 1, "bass": 1, "comp_vec": [1, null, 4, null, 8, null, null, null, null], "composition": [1, 4, 8], "quality": "m", "chord_type": 5, "chord_mode": -3, "isRest": false, "event_on": 0.0, "event_off": 4.0, "event_duration": 4.0, "inv": 0, "sus": null, "alter": null, "emb": [], "alter_map": null, "symbol": "dbm"}, {"root": 4, "bass": 11, "comp_vec": [16, null, 20, null, 11, null, null, null, null], "composition": [16, 20, 11], "quality": "", "chord_type": 5, "chord_mode": -3, "isRest": false, "event_on": 4.0, "event_off": 8.0, "event_duration": 4.0, "inv": 2, "sus": null, "alter": null, "emb": [], "alter_map": null, "symbol": "E | B"}, {"root": 10, "bass": 10, "comp_vec": [10, null, 13, null, 16, 20, null, null, null], "composition": [10, 13, 16, 20], "quality": "\u00f8", "chord_type": 7, "chord_mode": -2, "isRest": false, "event_on": 8.0, "event_off": 12.0, "event_duration": 4.0, "inv": 0, "sus": null, "alter": null, "emb": [], "alter_map": null, "symbol": "bb\u00f87"}, {"root": 9, "bass": 9, "comp_vec": [9, null, 13, null, 16, 20, null, null, null], "composition": [9, 13, 16, 20], "quality": "maj", "chord_type": 7, "chord_mode": -3, "isRest": false, "event_on": 12.0, "event_off": 16.0, "event_duration": 4.0, "inv": 0, "sus": null, "alter": null, "emb": [], "alter_map": null, "symbol": "Amaj7"}, {"root": 6, "bass": 6, "comp_vec": [6, null, 9, null, 13, null, 20, null, null], "composition": [6, 9, 13, 20], "quality": "m", "chord_type": 5, "chord_mode": -3, "isRest": false, "event_on": 16.0, "event_off": 20.0, "event_duration": 4.0, "inv": 0, "sus": null, "alter": null, "emb": ["add9"], "alter_map": null, "symbol": "gbm (add9)"}, {"root": 8, "bass": 8, "comp_vec": [8, null, 11, null, 15, null, null, null, null], "composition": [8, 11, 15], "quality": "m", "chord_type": 5, "chord_mode": -3, "isRest": false, "event_on": 20.0, "event_off": 24.0, "event_duration": 4.0, "inv": 0, "sus": null, "alter": null, "emb": [], "alter_map": null, "symbol": "abm"}, {"root": 9, "bass": 9, "comp_vec": [9, null, 13, null, 16, 20, null, null, null], "composition": [9, 13, 16, 20], "quality": "maj", "chord_type": 7, "chord_mode": -3, "isRest": false, "event_on": 24.0, "event_off": 28.0, "event_duration": 4.0, "inv": 0, "sus": null, "alter": null, "emb": [], "alter_map": null, "symbol": "Amaj7"}, {"root": 11, "bass": 11, "comp_vec": [11, null, 15, null, 18, null, null, null, null], "composition": [11, 15, 18], "quality": "", "chord_type": 5, "chord_mode": -3, "isRest": false, "event_on": 28.0, "event_off": 30.0, "event_duration": 2.0, "inv": 0, "sus": null, "alter": null, "emb": [], "alter_map": null, "symbol": "B"}, null, {"root": 1, "bass": 1, "comp_vec": [1, null, 4, null, 8, null, null, null, null], "composition": [1, 4, 8], "quality": "m", "chord_type": 5, "chord_mode": -3, "isRest": false, "event_on": 32.0, "event_off": 38.0, "event_duration": 6.0, "inv": 0, "sus": null, "alter": null, "emb": [], "alter_map": null, "symbol": "dbm"}, {"root": 1, "bass": 1, "comp_vec": [1, null, null, 6, 8, null, null, null, null], "composition": [1, 6, 8], "quality": "m", "chord_type": 5, "chord_mode": -3, "isRest": false, "event_on": 38.0, "event_off": 44.0, "event_duration": 6.0, "inv": 0, "sus": "sus4", "alter": null, "emb": [], "alter_map": null, "symbol": "dbm sus4"}, {"root": 1, "bass": 1, "comp_vec": [1, null, null, 6, 8, 11, null, null, null], "composition": [1, 6, 8, 11], "quality": "m", "chord_type": 7, "chord_mode": -3, "isRest": false, "event_on": 44.0, "event_off": 46.0, "event_duration": 2.0, "inv": 0, "sus": "sus4", "alter": null, "emb": [], "alter_map": null, "symbol": "dbm7 sus4"}, {"root": 1, "bass": 1, "comp_vec": [1, 3, null, null, 8, null, null, null, null], "composition": [1, 3, 8], "quality": "m", "chord_type": 5, "chord_mode": -3, "isRest": false, "event_on": 46.0, "event_off": 48.0, "event_duration": 2.0, "inv": 0, "sus": "sus2", "alter": null, "emb": [], "alter_map": null, "symbol": "dbm sus2"}, {"root": 9, "bass": 9, "comp_vec": [9, null, 13, null, 16, null, null, null, null], "composition": [9, 13, 16], "quality": "", "chord_type": 5, "chord_mode": -3, "isRest": false, "event_on": 48.0, "event_off": 50.0, "event_duration": 2.0, "inv": 0, "sus": null, "alter": null, "emb": [], "alter_map": null, "symbol": "A"}, {"root": 11, "bass": 11, "comp_vec": [11, null, 15, null, 18, null, null, null, null], "composition": [11, 15, 18], "quality": "", "chord_type": 5, "chord_mode": -3, "isRest": false, "event_on": 50.0, "event_off": 52.0, "event_duration": 2.0, "inv": 0, "sus": null, "alter": null, "emb": [], "alter_map": null, "symbol": "B"}, {"root": 9, "bass": 9, "comp_vec": [9, null, 13, null, 16, null, null, null, null], "composition": [9, 13, 16], "quality": "", "chord_type": 5, "chord_mode": -3, "isRest": false, "event_on": 52.0, "event_off": 54.0, "event_duration": 2.0, "inv": 0, "sus": null, "alter": null, "emb": [], "alter_map": null, "symbol": "A"}, {"root": 11, "bass": 11, "comp_vec": [11, null, 15, null, 18, null, null, null, null], "composition": [11, 15, 18], "quality": "", "chord_type": 5, "chord_mode": -3, "isRest": false, "event_on": 54.0, "event_off": 56.0, "event_duration": 2.0, "inv": 0, "sus": null, "alter": null, "emb": [], "alter_map": null, "symbol": "B"}, {"root": 10, "bass": 10, "comp_vec": [10, null, 13, null, 16, 20, null, null, null], "composition": [10, 13, 16, 20], "quality": "\u00f8", "chord_type": 7, "chord_mode": -2, "isRest": false, "event_on": 56.0, "event_off": 64.0, "event_duration": 8.0, "inv": 0, "sus": null, "alter": null, "emb": [], "alter_map": null, "symbol": "bb\u00f87"}, {"root": 9, "bass": 9, "comp_vec": [9, null, 13, null, 16, null, null, null, null], "composition": [9, 13, 16], "quality": "", "chord_type": 5, "chord_mode": -3, "isRest": false, "event_on": 64.0, "event_off": 76.0, "event_duration": 12.0, "inv": 0, "sus": null, "alter": null, "emb": [], "alter_map": null, "symbol": "A"}, {"root": 11, "bass": 21, "comp_vec": [23, null, 27, null, 30, 21, null, null, null], "composition": [23, 27, 30, 21], "quality": "", "chord_type": 7, "chord_mode": -3, "isRest": false, "event_on": 76.0, "event_off": 80.0, "event_duration": 4.0, "inv": 3, "sus": null, "alter": null, "emb": [], "alter_map": null, "symbol": "B7 | A"}, {"root": 1, "bass": 1, "comp_vec": [1, null, 4, null, 8, null, null, null, null], "composition": [1, 4, 8], "quality": "m", "chord_type": 5, "chord_mode": -3, "isRest": false, "event_on": 80.0, "event_off": 82.0, "event_duration": 2.0, "inv": 0, "sus": null, "alter": null, "emb": [], "alter_map": null, "symbol": "dbm"}, {"root": 1, "bass": 4, "comp_vec": [13, null, 4, null, 8, null, null, null, null], "composition": [13, 4, 8], "quality": "m", "chord_type": 5, "chord_mode": -3, "isRest": false, "event_on": 82.0, "event_off": 84.0, "event_duration": 2.0, "inv": 1, "sus": null, "alter": null, "emb": [], "alter_map": null, "symbol": "dbm | E"}, {"root": 0, "bass": 12, "comp_vec": [12, null, 15, null, 19, null, null, null, null], "composition": [12, 15, 19], "quality": "m", "chord_type": 5, "chord_mode": 1, "isRest": false, "event_on": 84.0, "event_off": 86.0, "event_duration": 2.0, "inv": 0, "sus": null, "alter": null, "emb": [], "alter_map": null, "symbol": "cm"}, {"root": 3, "bass": 3, "comp_vec": [3, null, 6, null, 9, null, null, null, null], "composition": [3, 6, 9], "quality": "o", "chord_type": 5, "chord_mode": -3, "isRest": false, "event_on": 86.0, "event_off": 88.0, "event_duration": 2.0, "inv": 0, "sus": null, "alter": null, "emb": [], "alter_map": null, "symbol": "ebo"}, {"root": 1, "bass": 1, "comp_vec": [1, null, 4, null, 8, null, null, null, null], "composition": [1, 4, 8], "quality": "m", "chord_type": 5, "chord_mode": -3, "isRest": false, "event_on": 88.0, "event_off": 90.0, "event_duration": 2.0, "inv": 0, "sus": null, "alter": null, "emb": [], "alter_map": null, "symbol": "dbm"}, {"root": 1, "bass": 4, "comp_vec": [13, null, 4, null, 8, null, null, null, null], "composition": [13, 4, 8], "quality": "m", "chord_type": 5, "chord_mode": -3, "isRest": false, "event_on": 90.0, "event_off": 92.0, "event_duration": 2.0, "inv": 1, "sus": null, "alter": null, "emb": [], "alter_map": null, "symbol": "dbm | E"}, {"root": 0, "bass": 12, "comp_vec": [12, null, 15, null, 19, null, null, null, null], "composition": [12, 15, 19], "quality": "m", "chord_type": 5, "chord_mode": 1, "isRest": false, "event_on": 92.0, "event_off": 94.0, "event_duration": 2.0, "inv": 0, "sus": null, "alter": null, "emb": [], "alter_map": null, "symbol": "cm"}, {"root": 3, "bass": 3, "comp_vec": [3, null, 6, null, 9, null, null, null, null], "composition": [3, 6, 9], "quality": "o", "chord_type": 5, "chord_mode": -3, "isRest": false, "event_on": 94.0, "event_off": 96.0, "event_duration": 2.0, "inv": 0, "sus": null, "alter": null, "emb": [], "alter_map": null, "symbol": "ebo"}]}, "num_measures": 24.0}