{"version": null, "metadata": {"title": "New Project 6 Beats Per Measure", "beats_in_measure": "6", "BPM": "240", "key": "F", "YouTubeID": "q7yCLn-O-Y0", "mode": "1", "duration": "21.4"}, "tracks": {"melody": [null, {"pitch": 9.0, "isRest": false, "event_on": 4.0, "event_off": 5.0, "event_duration": 1.0}, {"pitch": 10.0, "isRest": false, "event_on": 5.0, "event_off": 6.0, "event_duration": 1.0}, {"pitch": 12.0, "isRest": false, "event_on": 6.0, "event_off": 8.0, "event_duration": 2.0}, {"pitch": 9.0, "isRest": false, "event_on": 8.0, "event_off": 9.0, "event_duration": 1.0}, {"pitch": 12.0, "isRest": false, "event_on": 9.0, "event_off": 11.0, "event_duration": 2.0}, {"pitch": 12.0, "isRest": false, "event_on": 11.0, "event_off": 12.0, "event_duration": 1.0}, {"pitch": 12.0, "isRest": false, "event_on": 12.0, "event_off": 14.0, "event_duration": 2.0}, {"pitch": 12.0, "isRest": false, "event_on": 14.0, "event_off": 15.0, "event_duration": 1.0}, {"pitch": 12.0, "isRest": false, "event_on": 15.0, "event_off": 16.0, "event_duration": 1.0}, {"pitch": 10.0, "isRest": false, "event_on": 16.0, "event_off": 17.0, "event_duration": 1.0}, {"pitch": 9.0, "isRest": false, "event_on": 17.0, "event_off": 18.0, "event_duration": 1.0}, {"pitch": 10.0, "isRest": false, "event_on": 18.0, "event_off": 21.0, "event_duration": 2.9999999999999982}, null, {"pitch": 5.0, "isRest": false, "event_on": 23.0, "event_off": 24.0, "event_duration": 1.0}, {"pitch": 14.0, "isRest": false, "event_on": 24.0, "event_off": 25.0, "event_duration": 1.0}, {"pitch": 14.0, "isRest": false, "event_on": 25.0, "event_off": 26.0, "event_duration": 1.0}, {"pitch": 14.0, "isRest": false, "event_on": 26.0, "event_off": 27.0, "event_duration": 1.0}, {"pitch": 12.0, "isRest": false, "event_on": 27.0, "event_off": 29.0, "event_duration": 2.0}, {"pitch": 10.0, "isRest": false, "event_on": 29.0, "event_off": 30.0, "event_duration": 1.0}, {"pitch": 12.0, "isRest": false, "event_on": 30.0, "event_off": 31.0, "event_duration": 1.0}, {"pitch": 9.0, "isRest": false, "event_on": 31.0, "event_off": 33.0, "event_duration": 2.0}, null, {"pitch": 9.0, "isRest": false, "event_on": 52.0, "event_off": 53.0, "event_duration": 1.0}, {"pitch": 10.0, "isRest": false, "event_on": 53.0, "event_off": 54.0, "event_duration": 1.0}, {"pitch": 12.0, "isRest": false, "event_on": 54.0, "event_off": 56.0, "event_duration": 2.0}, {"pitch": 9.0, "isRest": false, "event_on": 56.0, "event_off": 57.0, "event_duration": 1.0}, {"pitch": 12.0, "isRest": false, "event_on": 57.0, "event_off": 59.0, "event_duration": 2.0}, {"pitch": 12.0, "isRest": false, "event_on": 59.0, "event_off": 60.0, "event_duration": 1.0}, {"pitch": 12.0, "isRest": false, "event_on": 60.0, "event_off": 61.0, "event_duration": 1.0}, {"pitch": 12.0, "isRest": false, "event_on": 61.0, "event_off": 62.0, "event_duration": 1.0}, {"pitch": 9.0, "isRest": false, "event_on": 62.0, "event_off": 63.0, "event_duration": 1.0}, {"pitch": 12.0, "isRest": false, "event_on": 63.0, "event_off": 65.0, "event_duration": 2.0}, {"pitch": 9.0, "isRest": false, "event_on": 65.0, "event_off": 66.0, "event_duration": 1.0}, {"pitch": 10.0, "isRest": false, "event_on": 66.0, "event_off": 68.0, "event_duration": 2.0}, {"pitch": 9.0, "isRest": false, "event_on": 68.0, "event_off": 69.0, "event_duration": 1.0}, {"pitch": 7.0, "isRest": false, "event_on": 69.0, "event_off": 70.0, "event_duration": 1.0}, {"pitch": 7.0, "isRest": false, "event_on": 70.0, "event_off": 71.0, "event_duration": 1.0}, {"pitch": 0.0, "isRest": false, "event_on": 71.0, "event_off": 72.0, "event_duration": 1.0}, {"pitch": 10.0, "isRest": false, "event_on": 72.0, "event_off": 73.0, "event_duration": 1.0}, {"pitch": 10.0, "isRest": false, "event_on": 73.0, "event_off": 74.0, "event_duration": 1.0}, {"pitch": 10.0, "isRest": false, "event_on": 74.0, "event_off": 75.0, "event_duration": 1.0}, {"pitch": 10.0, "isRest": false, "event_on": 75.0, "event_off": 76.0, "event_duration": 1.0}, {"pitch": 9.0, "isRest": false, "event_on": 76.0, "event_off": 77.0, "event_duration": 1.0}, {"pitch": 7.0, "isRest": false, "event_on": 77.0, "event_off": 78.0, "event_duration": 1.0}, {"pitch": 5.0, "isRest": false, "event_on": 78.0, "event_off": 80.0, "event_duration": 2.0}], "chord": [{"root": 5, "bass": 5, "comp_vec": [5, null, 9, null, 12, null, null, null, null], "composition": [5, 9, 12], "quality": "", "chord_type": 5, "chord_mode": 0, "isRest": false, "event_on": 6.0, "event_off": 18.0, "event_duration": 12.0, "inv": 0, "sus": null, "alter": null, "emb": [], "alter_map": null, "symbol": "F"}, {"root": 10, "bass": 10, "comp_vec": [10, null, 14, null, 17, null, null, null, null], "composition": [10, 14, 17], "quality": "", "chord_type": 5, "chord_mode": 0, "isRest": false, "event_on": 18.0, "event_off": 30.0, "event_duration": 12.0, "inv": 0, "sus": null, "alter": null, "emb": [], "alter_map": null, "symbol": "Bb"}, {"root": 5, "bass": 5, "comp_vec": [5, null, 9, null, 12, null, null, null, null], "composition": [5, 9, 12], "quality": "", "chord_type": 5, "chord_mode": 0, "isRest": false, "event_on": 30.0, "event_off": 42.0, "event_duration": 12.0, "inv": 0, "sus": null, "alter": null, "emb": [], "alter_map": null, "symbol": "F"}, {"root": 10, "bass": 10, "comp_vec": [10, null, 14, null, 17, null, null, null, null], "composition": [10, 14, 17], "quality": "", "chord_type": 5, "chord_mode": 0, "isRest": false, "event_on": 42.0, "event_off": 54.0, "event_duration": 12.0, "inv": 0, "sus": null, "alter": null, "emb": [], "alter_map": null, "symbol": "Bb"}, {"root": 5, "bass": 5, "comp_vec": [5, null, 9, null, 12, null, null, null, null], "composition": [5, 9, 12], "quality": "", "chord_type": 5, "chord_mode": 0, "isRest": false, "event_on": 54.0, "event_off": 66.0, "event_duration": 12.0, "inv": 0, "sus": null, "alter": null, "emb": [], "alter_map": null, "symbol": "F"}, {"root": 10, "bass": 10, "comp_vec": [10, null, 14, null, 17, null, null, null, null], "composition": [10, 14, 17], "quality": "", "chord_type": 5, "chord_mode": 0, "isRest": false, "event_on": 66.0, "event_off": 78.0, "event_duration": 12.0, "inv": 0, "sus": null, "alter": null, "emb": [], "alter_map": null, "symbol": "Bb"}, {"root": 5, "bass": 5, "comp_vec": [5, null, 9, null, 12, null, null, null, null], "composition": [5, 9, 12], "quality": "", "chord_type": 5, "chord_mode": 0, "isRest": false, "event_on": 78.0, "event_off": 90.0, "event_duration": 12.0, "inv": 0, "sus": null, "alter": null, "emb": [], "alter_map": null, "symbol": "F"}, {"root": 10, "bass": 10, "comp_vec": [10, null, 14, null, 17, null, null, null, null], "composition": [10, 14, 17], "quality": "", "chord_type": 5, "chord_mode": 0, "isRest": false, "event_on": 90.0, "event_off": 102.0, "event_duration": 12.0, "inv": 0, "sus": null, "alter": null, "emb": [], "alter_map": null, "symbol": "Bb"}]}, "num_measures": 17.0}