{"version": "1.3", "metadata": {"title": "Untitled", "beats_in_measure": "4", "BPM": "95", "key": "Bb", "YouTubeID": "5tS6caxOlTY", "mode": "1", "duration": "35.35"}, "tracks": {"melody": [], "chord": [{"root": 7, "bass": 19, "comp_vec": [19, null, 22, null, 26, null, null, null, null], "composition": [19, 22, 26], "quality": "m", "chord_type": 5, "chord_mode": 0, "isRest": false, "event_on": 0.0, "event_off": 4.0, "event_duration": 4.0, "inv": 0, "sus": null, "alter": null, "emb": [], "alter_map": null, "symbol": "gm"}, {"root": 2, "bass": 14, "comp_vec": [14, null, 17, null, 21, null, null, null, null], "composition": [14, 17, 21], "quality": "m", "chord_type": 5, "chord_mode": 0, "isRest": false, "event_on": 4.0, "event_off": 8.0, "event_duration": 4.0, "inv": 0, "sus": null, "alter": null, "emb": [], "alter_map": null, "symbol": "dm"}, {"root": 7, "bass": 19, "comp_vec": [19, null, 22, null, 26, null, null, null, null], "composition": [19, 22, 26], "quality": "m", "chord_type": 5, "chord_mode": 0, "isRest": false, "event_on": 8.0, "event_off": 12.0, "event_duration": 4.0, "inv": 0, "sus": null, "alter": null, "emb": [], "alter_map": null, "symbol": "gm"}, {"root": 2, "bass": 14, "comp_vec": [14, null, 17, null, 21, null, null, null, null], "composition": [14, 17, 21], "quality": "m", "chord_type": 5, "chord_mode": 0, "isRest": false, "event_on": 12.0, "event_off": 16.0, "event_duration": 4.0, "inv": 0, "sus": null, "alter": null, "emb": [], "alter_map": null, "symbol": "dm"}, {"root": 3, "bass": 15, "comp_vec": [15, null, 19, null, 22, null, null, null, null], "composition": [15, 19, 22], "quality": "", "chord_type": 5, "chord_mode": 0, "isRest": false, "event_on": 16.0, "event_off": 20.0, "event_duration": 4.0, "inv": 0, "sus": null, "alter": null, "emb": [], "alter_map": null, "symbol": "Eb"}, {"root": 2, "bass": 14, "comp_vec": [14, null, 17, null, 21, null, null, null, null], "composition": [14, 17, 21], "quality": "m", "chord_type": 5, "chord_mode": 0, "isRest": false, "event_on": 20.0, "event_off": 24.0, "event_duration": 4.0, "inv": 0, "sus": null, "alter": null, "emb": [], "alter_map": null, "symbol": "dm"}, {"root": 7, "bass": 19, "comp_vec": [19, null, 22, null, 26, null, null, null, null], "composition": [19, 22, 26], "quality": "m", "chord_type": 5, "chord_mode": 0, "isRest": false, "event_on": 24.0, "event_off": 28.0, "event_duration": 4.0, "inv": 0, "sus": null, "alter": null, "emb": [], "alter_map": null, "symbol": "gm"}, {"root": 2, "bass": 14, "comp_vec": [14, null, 17, null, 21, null, null, null, null], "composition": [14, 17, 21], "quality": "m", "chord_type": 5, "chord_mode": 0, "isRest": false, "event_on": 28.0, "event_off": 32.0, "event_duration": 4.0, "inv": 0, "sus": null, "alter": null, "emb": [], "alter_map": null, "symbol": "dm"}, {"root": 7, "bass": 19, "comp_vec": [19, null, 22, null, 26, null, null, null, null], "composition": [19, 22, 26], "quality": "m", "chord_type": 5, "chord_mode": 0, "isRest": false, "event_on": 32.0, "event_off": 36.0, "event_duration": 4.0, "inv": 0, "sus": null, "alter": null, "emb": [], "alter_map": null, "symbol": "gm"}, {"root": 2, "bass": 14, "comp_vec": [14, null, 17, null, 21, null, null, null, null], "composition": [14, 17, 21], "quality": "m", "chord_type": 5, "chord_mode": 0, "isRest": false, "event_on": 36.0, "event_off": 40.0, "event_duration": 4.0, "inv": 0, "sus": null, "alter": null, "emb": [], "alter_map": null, "symbol": "dm"}, {"root": 3, "bass": 15, "comp_vec": [15, null, 19, null, 22, null, null, null, null], "composition": [15, 19, 22], "quality": "", "chord_type": 5, "chord_mode": 0, "isRest": false, "event_on": 40.0, "event_off": 44.0, "event_duration": 4.0, "inv": 0, "sus": null, "alter": null, "emb": [], "alter_map": null, "symbol": "Eb"}, {"root": 2, "bass": 14, "comp_vec": [14, null, 17, null, 21, null, null, null, null], "composition": [14, 17, 21], "quality": "m", "chord_type": 5, "chord_mode": 0, "isRest": false, "event_on": 44.0, "event_off": 48.0, "event_duration": 4.0, "inv": 0, "sus": null, "alter": null, "emb": [], "alter_map": null, "symbol": "dm"}]}, "num_measures": 12.0}