{"version": "1.3", "metadata": {"title": "Huilend Naar De Club", "beats_in_measure": "4", "BPM": "105", "key": "C", "YouTubeID": "s4rzYABlH5o", "mode": "6", "duration": "21.11"}, "tracks": {"melody": [{"pitch": 0.0, "isRest": false, "event_on": 0.0, "event_off": 2.0, "event_duration": 2.0}, {"pitch": 5.0, "isRest": false, "event_on": 2.0, "event_off": 4.0, "event_duration": 2.0}, {"pitch": 3.0, "isRest": false, "event_on": 4.0, "event_off": 6.0, "event_duration": 2.0}, {"pitch": -2.0, "isRest": false, "event_on": 6.0, "event_off": 8.0, "event_duration": 2.0}, {"pitch": -4.0, "isRest": false, "event_on": 8.0, "event_off": 16.0, "event_duration": 8.0}, {"pitch": 0.0, "isRest": false, "event_on": 16.0, "event_off": 18.0, "event_duration": 2.0}, {"pitch": 5.0, "isRest": false, "event_on": 18.0, "event_off": 20.0, "event_duration": 2.0}, {"pitch": 3.0, "isRest": false, "event_on": 20.0, "event_off": 22.0, "event_duration": 2.0}, {"pitch": -2.0, "isRest": false, "event_on": 22.0, "event_off": 24.0, "event_duration": 2.0}, {"pitch": 3.0, "isRest": false, "event_on": 24.0, "event_off": 32.0, "event_duration": 8.0}], "chord": [{"root": 5, "bass": 5, "comp_vec": [5, null, 8, null, 12, null, null, null, null], "composition": [5, 8, 12], "quality": "m", "chord_type": 5, "chord_mode": -3, "isRest": false, "event_on": 0.0, "event_off": 2.0, "event_duration": 2.0, "inv": 0, "sus": null, "alter": null, "emb": [], "alter_map": null, "symbol": "fm"}, {"root": 5, "bass": 5, "comp_vec": [5, null, 8, null, 12, null, null, null, null], "composition": [5, 8, 12], "quality": "m", "chord_type": 5, "chord_mode": -3, "isRest": false, "event_on": 2.0, "event_off": 4.0, "event_duration": 2.0, "inv": 0, "sus": null, "alter": null, "emb": [], "alter_map": null, "symbol": "fm"}, {"root": 3, "bass": 3, "comp_vec": [3, null, 7, null, 10, null, null, null, null], "composition": [3, 7, 10], "quality": "", "chord_type": 5, "chord_mode": -3, "isRest": false, "event_on": 4.0, "event_off": 6.0, "event_duration": 2.0, "inv": 0, "sus": null, "alter": null, "emb": [], "alter_map": null, "symbol": "Eb"}, {"root": 3, "bass": 3, "comp_vec": [3, null, 7, null, 10, null, null, null, null], "composition": [3, 7, 10], "quality": "", "chord_type": 5, "chord_mode": -3, "isRest": false, "event_on": 6.0, "event_off": 8.0, "event_duration": 2.0, "inv": 0, "sus": null, "alter": null, "emb": [], "alter_map": null, "symbol": "Eb"}, {"root": 1, "bass": 13, "comp_vec": [13, null, 17, null, 20, null, null, null, null], "composition": [13, 17, 20], "quality": "", "chord_type": 5, "chord_mode": 0, "isRest": false, "event_on": 8.0, "event_off": 16.0, "event_duration": 8.0, "inv": 0, "sus": null, "alter": null, "emb": [], "alter_map": null, "symbol": "Db"}, {"root": 5, "bass": 5, "comp_vec": [5, null, 8, null, 12, null, null, null, null], "composition": [5, 8, 12], "quality": "m", "chord_type": 5, "chord_mode": -3, "isRest": false, "event_on": 16.0, "event_off": 18.0, "event_duration": 2.0, "inv": 0, "sus": null, "alter": null, "emb": [], "alter_map": null, "symbol": "fm"}, {"root": 5, "bass": 5, "comp_vec": [5, null, 8, null, 12, null, null, null, null], "composition": [5, 8, 12], "quality": "m", "chord_type": 5, "chord_mode": -3, "isRest": false, "event_on": 18.0, "event_off": 20.0, "event_duration": 2.0, "inv": 0, "sus": null, "alter": null, "emb": [], "alter_map": null, "symbol": "fm"}, {"root": 3, "bass": 3, "comp_vec": [3, null, 7, null, 10, null, null, null, null], "composition": [3, 7, 10], "quality": "", "chord_type": 5, "chord_mode": -3, "isRest": false, "event_on": 20.0, "event_off": 22.0, "event_duration": 2.0, "inv": 0, "sus": null, "alter": null, "emb": [], "alter_map": null, "symbol": "Eb"}, {"root": 3, "bass": 3, "comp_vec": [3, null, 7, null, 10, null, null, null, null], "composition": [3, 7, 10], "quality": "", "chord_type": 5, "chord_mode": -3, "isRest": false, "event_on": 22.0, "event_off": 24.0, "event_duration": 2.0, "inv": 0, "sus": null, "alter": null, "emb": [], "alter_map": null, "symbol": "Eb"}, {"root": 1, "bass": 13, "comp_vec": [13, null, 17, null, 20, null, null, null, null], "composition": [13, 17, 20], "quality": "", "chord_type": 5, "chord_mode": 0, "isRest": false, "event_on": 24.0, "event_off": 32.0, "event_duration": 8.0, "inv": 0, "sus": null, "alter": null, "emb": [], "alter_map": null, "symbol": "Db"}]}, "num_measures": 8.0}